{
  "bounds": {
    "max": [
      65.0,
      10.8,
      7.500007629510948
    ],
    "min": [
      -65.0,
      0.0,
      -7.499992370489052
    ]
  },
  "center": [
    0.0,
    0.0,
    0.0
  ],
  "points": [
    [
      -65.0,
      0.0,
      7.500007629510948
    ],
    [
      -61.67498283360037,
      5.6,
      -2.149980926222629
    ],
    [
      -61.67498283360037,
      5.6,
      5.3499961852445255
    ],
    [
      -45.424979018844894,
      5.6,
      5.3499961852445255
    ],
    [
      -32.49999237048905,
      0.0,
      7.500007629510948
    ],
    [
      -51.83999389639124,
      10.8,
      2.159990844586862
    ],
    [
      -45.424979018844894,
      5.6,
      -2.149980926222629
    ],
    [
      -32.49999237048905,
      0.0,
      -7.499992370489052
    ],
    [
      -28.074982833600366,
      4.8,
      -5.349980926222629
    ],
    [
      -28.074982833600366,
      4.8,
      4.549996185244526
    ],
    [
      -7.024979018844892,
      2.0,
      -5.349980926222629
    ],
    [
      0.0,
      0.0,
      7.500007629510948
    ],
    [
      -7.024979018844892,
      2.0,
      4.549996185244526
    ],
    [
      0.0,
      0.0,
      -7.499992370489052
    ],
    [
      11.925001907377737,
      3.2,
      4.549996185244526
    ],
    [
      27.2,
      6.4,
      0.15999084458686197
    ],
    [
      42.57500572213321,
      3.2,
      4.549996185244526
    ],
    [
      42.57500572213321,
      3.2,
      -3.749996185244526
    ],
    [
      65.0,
      0.0,
      -7.499992370489052
    ],
    [
      -65.0,
      0.0,
      -7.499992370489052
    ],
    [
      -19.839993896391242,
      8.0,
      0.9600061036087587
    ],
    [
      11.925001907377737,
      3.2,
      -3.749996185244526
    ],
    [
      65.0,
      0.0,
      7.500007629510948
    ],
    [
      -19.66129549095903,
      7.916334782940414,
      1.010055695429923
    ],
    [
      0.0,
      0.0,
      5.440573739223316
    ],
    [
      -32.49999237048905,
      0.0,
      -6.791531242847333
    ]
  ],
  "polys": [
    {
      "color": 16711422,
      "normal": [
        0.8598611429007401,
        -0.5105210955977721,
        0.0
      ],
      "tris": [
        [
          2,
          19,
          0
        ]
      ]
    },
    {
      "color": 16711422,
      "normal": [
        0.8598611429007401,
        -0.5105210955977721,
        0.0
      ],
      "tris": [
        [
          19,
          2,
          1
        ]
      ]
    },
    {
      "color": 16711422,
      "normal": [
        0.4674143587396048,
        -0.8840314335851072,
        0.0
      ],
      "tris": [
        [
          5,
          1,
          2
        ]
      ]
    },
    {
      "color": 16711422,
      "normal": [
        0.0,
        -0.3584039063096055,
        -0.9335469596398871
      ],
      "tris": [
        [
          3,
          2,
          0
        ]
      ]
    },
    {
      "color": 16711422,
      "normal": [
        0.0,
        -0.5228961623559929,
        -0.8523842221713588
      ],
      "tris": [
        [
          2,
          3,
          5
        ]
      ]
    },
    {
      "color": 16711422,
      "normal": [
        0.0,
        -0.3584039063096055,
        -0.9335469596398871
      ],
      "tris": [
        [
          4,
          3,
          0
        ]
      ]
    },
    {
      "color": 16711422,
      "normal": [
        0.7352407110704204,
        -0.6777904936293584,
        0.0
      ],
      "tris": [
        [
          8,
          7,
          4
        ]
      ]
    },
    {
      "color": 16711422,
      "normal": [
        0.7352407110704204,
        -0.6777904936293584,
        0.0
      ],
      "tris": [
        [
          8,
          4,
          9
        ]
      ]
    },
    {
      "color": 16711422,
      "normal": [
        0.36220340276188295,
        -0.9320973525597009,
        0.0
      ],
      "tris": [
        [
          20,
          8,
          9
        ]
      ]
    },
    {
      "color": 16711422,
      "normal": [
        0.0,
        -0.5235828183413443,
        -0.8519569695582513
      ],
      "tris": [
        [
          11,
          9,
          4
        ]
      ]
    },
    {
      "color": 16711422,
      "normal": [
        0.25917448691538875,
        -0.9658197909514,
        0.0
      ],
      "tris": [
        [
          13,
          11,
          14
        ]
      ]
    },
    {
      "color": 16711422,
      "normal": [
        0.25917448691538875,
        -0.9658197909514,
        0.0
      ],
      "tris": [
        [
          14,
          21,
          13
        ]
      ]
    },
    {
      "color": 16711422,
      "normal": [
        0.2050354772259098,
        -0.9787441824979018,
        0.0
      ],
      "tris": [
        [
          15,
          21,
          14
        ]
      ]
    },
    {
      "color": 16711422,
      "normal": [
        0.0,
        -0.6777904936293584,
        -0.7352254520485237
      ],
      "tris": [
        [
          16,
          14,
          11
        ]
      ]
    },
    {
      "color": 16711422,
      "normal": [
        0.0,
        -0.7606775005722133,
        0.6491187914854658
      ],
      "tris": [
        [
          18,
          13,
          21
        ]
      ]
    },
    {
      "color": 16711422,
      "normal": [
        0.0,
        -0.7738612954909591,
        0.6333409628442817
      ],
      "tris": [
        [
          21,
          15,
          17
        ]
      ]
    },
    {
      "color": 16711422,
      "normal": [
        0.0,
        -0.8080872816052491,
        -0.5890287632562753
      ],
      "tris": [
        [
          16,
          15,
          14
        ]
      ]
    },
    {
      "color": 16711422,
      "normal": [
        0.0,
        -0.6777904936293584,
        -0.7352254520485237
      ],
      "tris": [
        [
          22,
          16,
          11
        ]
      ]
    },
    {
      "color": 16711422,
      "normal": [
        0.0,
        -0.7606775005722133,
        0.6491187914854658
      ],
      "tris": [
        [
          18,
          21,
          17
        ]
      ]
    },
    {
      "color": 16711422,
      "normal": [
        -0.20373846036469068,
        -0.9790188448920424,
        0.0
      ],
      "tris": [
        [
          17,
          15,
          16
        ]
      ]
    },
    {
      "color": 16711422,
      "normal": [
        -0.14125276569771883,
        -0.9899595635919738,
        0.0
      ],
      "tris": [
        [
          18,
          17,
          16
        ]
      ]
    },
    {
      "color": 16711422,
      "normal": [
        -0.14125276569771883,
        -0.9899595635919738,
        0.0
      ],
      "tris": [
        [
          22,
          18,
          16
        ]
      ]
    },
    {
      "color": 16711422,
      "normal": [
        -0.0849774929427024,
        -0.6389562829022659,
        -0.7645075150682841
      ],
      "tris": [
        [
          9,
          12,
          20
        ]
      ]
    },
    {
      "color": 16711422,
      "normal": [
        0.0,
        -0.7321736476691845,
        0.6811017013809415
      ],
      "tris": [
        [
          13,
          7,
          10
        ]
      ]
    },
    {
      "color": 16711422,
      "normal": [
        -0.4240024414435035,
        -0.9056382085908293,
        0.0
      ],
      "tris": [
        [
          23,
          12,
          10
        ]
      ]
    },
    {
      "color": 16711422,
      "normal": [
        -0.2737926298924239,
        -0.9617761501487755,
        0.0
      ],
      "tris": [
        [
          13,
          10,
          12
        ]
      ]
    },
    {
      "color": 16711422,
      "normal": [
        -0.2737926298924239,
        -0.9617761501487755,
        0.0
      ],
      "tris": [
        [
          13,
          12,
          24
        ]
      ]
    },
    {
      "color": 16711422,
      "normal": [
        -0.04921034561684601,
        -0.3701228351262684,
        0.927672236209659
      ],
      "tris": [
        [
          10,
          7,
          8
        ]
      ]
    },
    {
      "color": 16711422,
      "normal": [
        -0.10928511482413972,
        -0.8216830701152056,
        0.5593499656672007
      ],
      "tris": [
        [
          8,
          20,
          10
        ]
      ]
    },
    {
      "color": 16711422,
      "normal": [
        -0.4240024414435035,
        -0.9056382085908293,
        0.0
      ],
      "tris": [
        [
          20,
          23,
          10
        ]
      ]
    },
    {
      "color": 16711422,
      "normal": [
        -0.1241168841077287,
        -0.9332417792019532,
        -0.337071793698024
      ],
      "tris": [
        [
          11,
          12,
          9
        ]
      ]
    },
    {
      "color": 16711422,
      "normal": [
        -0.2737926298924239,
        -0.9617761501487755,
        0.0
      ],
      "tris": [
        [
          12,
          11,
          24
        ]
      ]
    },
    {
      "color": 16711422,
      "normal": [
        0.0,
        -0.6381322957198443,
        0.7699244678416114
      ],
      "tris": [
        [
          6,
          1,
          5
        ]
      ]
    },
    {
      "color": 16711422,
      "normal": [
        -0.6296940566109712,
        -0.7768215457389182,
        0.0
      ],
      "tris": [
        [
          6,
          5,
          3
        ]
      ]
    },
    {
      "color": 16711422,
      "normal": [
        -0.3975432974746319,
        -0.9175707637140459,
        0.0
      ],
      "tris": [
        [
          6,
          3,
          4
        ]
      ]
    },
    {
      "color": 16711422,
      "normal": [
        -0.3975432974746319,
        -0.9175707637140459,
        0.0
      ],
      "tris": [
        [
          6,
          4,
          25
        ]
      ]
    },
    {
      "color": 16711422,
      "normal": [
        0.0,
        -0.690775921263447,
        0.7230640115968566
      ],
      "tris": [
        [
          19,
          1,
          7
        ]
      ]
    },
    {
      "color": 16711422,
      "normal": [
        0.0,
        -0.690775921263447,
        0.7230640115968566
      ],
      "tris": [
        [
          7,
          1,
          6
        ]
      ]
    },
    {
      "color": 16711422,
      "normal": [
        -0.3975432974746319,
        -0.9175707637140459,
        0.0
      ],
      "tris": [
        [
          6,
          25,
          7
        ]
      ]
    }
  ],
  "radius1": 65.43126573586633,
  "radius2": 65.43126573586633
}
